discordlogger/__init__.py
discordlogger-0.0.2.dist-info/LICENSE
discordlogger-0.0.2.dist-info/METADATA
discordlogger-0.0.2.dist-info/WHEEL
discordlogger-0.0.2.dist-info/top_level.txt
discordlogger-0.0.2.dist-info/RECORD
