Metadata-Version: 2.1
Name: discordlogger
Version: 0.0.2
Summary: A Python logger to send information to Discord Webhooks.
Home-page: https://github.com/2press/discord-logger
Author: pressure
Author-email: pres.sure@ymail.com
License: MIT
Platform: UNKNOWN
Requires-Dist: requests
